{ "commands": [
{ "hdr": "242", "rax": "642", "cmd": {"22": "2A4074"}, "freq": 0.25,
  "signals": [
    {"id": "SPARK_STEER_ANGLE", "path": "Control", "fmt": { "len": 16, "sign": true, "min": -540, "max": 540, "div": 16, "unit": "degrees" }, "name": "Steering wheel angle" }
  ]},
{ "hdr": "242", "rax": "642", "cmd": {"22": "2A40AC"}, "freq": 0.25,
  "signals": [
    {"id": "SPARK_STEER_INPUT_TORQUE", "path": "Control", "fmt": { "len": 16, "sign": true, "div": 100, "unit": "newtonMeters" }, "name": "Steering input torque" }
  ]},
{ "hdr": "243", "rax": "643", "cmd": {"22": "2A4051"}, "freq": 0.25,
  "signals": [
    {"id": "SPARK_FL_WHEEL_SPD", "path": "Movement", "fmt": { "len": 8, "unit": "kilometersPerHour" }, "name": "Front left wheel speed?" }
  ]},
{ "hdr": "243", "rax": "643", "cmd": {"22": "2A4052"}, "freq": 0.25,
  "signals": [
    {"id": "SPARK_FR_WHEEL_SPD", "path": "Movement", "fmt": { "len": 8, "unit": "kilometersPerHour" }, "name": "Front right wheel speed?" }
  ]},
{ "hdr": "243", "rax": "643", "cmd": {"22": "2A4053"}, "freq": 0.25,
  "signals": [
    {"id": "SPARK_RL_WHEEL_SPD", "path": "Movement", "fmt": { "len": 8, "unit": "kilometersPerHour" }, "name": "Rear left wheel speed?" }
  ]},
{ "hdr": "243", "rax": "643", "cmd": {"22": "2A4051"}, "freq": 0.25,
  "signals": [
    {"id": "SPARK_FL_WHEEL_SPD", "path": "Movement", "fmt": { "len": 8, "unit": "kilometersPerHour" }, "name": "Front left wheel speed?" }
  ]},
{ "hdr": "241", "rax": "641", "cmd": {"22": "2290FB"}, "freq": 0.25,
  "signals": [
    {"id": "SPARK_12V_C", "path": "Battery", "fmt": { "len": 16, "sign": true, "mul": 0.01, "unit": "amps" }, "name": "12V battery current" }
  ]},
{ "hdr": "241", "rax": "641", "cmd": {"22": "2290B1"}, "freq": 0.25,
  "signals": [
    {"id": "SPARK_12V_V", "path": "Battery", "fmt": { "len": 16, "mul": 0.001, "unit": "volts", "suggestedMetricEnum": "starterBatteryVoltage" }, "name": "12V battery voltage" }
  ]},
{ "hdr": "241", "rax": "641", "cmd": {"22": "2290F8"}, "freq": 0.25,
  "signals": [
    {"id": "SPARK_12V_SOC", "path": "Battery", "fmt": { "len": 16, "div": 32767, "mul": 100, "unit": "percent", "suggestedMetricEnum": "stateOfCharge"}, "name": "12V battery state of charge" }
  ]}
]
}
